MANIFEST.in
README.txt
setup.py
wiselib2/EasyStart.py
wiselib2/FermiSource.py
wiselib2/Fundation.py
wiselib2/Noise.py
wiselib2/Optics.py
wiselib2/Rayman.py
wiselib2/ToolLib.py
wiselib2/__init__.py
wiselib2/must.py
wiselib2/version.py
wiselib2.egg-info/PKG-INFO
wiselib2.egg-info/SOURCES.txt
wiselib2.egg-info/dependency_links.txt
wiselib2.egg-info/not-zip-safe
wiselib2.egg-info/requires.txt
wiselib2.egg-info/top_level.txt